{"content": {"suites": {"0": {"status": {"total_pass": 3, "total_skip": 0, "total_xpass": 0, "total_xfail": 0, "total_rerun": 0, "total_fail": 8, "total_error": 0}, "tests": {"0": {"status": "PASS", "message": "", "test_name": "test_Convert", "rerun": "0"}, "1": {"status": "PASS", "message": "", "test_name": "test_get_allBalance", "rerun": "0"}, "2": {"status": "FAIL", "message": "       json.decoder.JSONDecodeError: Expecting value: line 1 column 1 (char 0)\n               requests.exceptions.JSONDecodeError: Expecting value: line 1 column 1 (char 0)\n", "test_name": "test_get_Beneficiary", "rerun": "0"}, "3": {"status": "FAIL", "message": "       json.decoder.JSONDecodeError: Expecting value: line 1 column 1 (char 0)\n               requests.exceptions.JSONDecodeError: Expecting value: line 1 column 1 (char 0)\n", "test_name": "test_get_Beneficiary_id", "rerun": "0"}, "4": {"status": "PASS", "message": "", "test_name": "test_get_Bank_to_deposit", "rerun": "0"}, "5": {"status": "FAIL", "message": "   AssertionError: 401 != 200 within 7 places (201 difference) : Fail\n", "test_name": "test_Bank_to_deposit", "rerun": "0"}, "6": {"status": "FAIL", "message": "   AssertionError: 401 != 200 within 7 places (201 difference) : FAIL\n", "test_name": "test_Convert", "rerun": "0"}, "7": {"status": "FAIL", "message": "       json.decoder.JSONDecodeError: Expecting value: line 1 column 1 (char 0)\n               requests.exceptions.JSONDecodeError: Expecting value: line 1 column 1 (char 0)\n", "test_name": "test_GetByBene_by_id", "rerun": "0"}, "8": {"status": "FAIL", "message": "               AssertionError: 401 != 200 within 7 places (201 difference) : FAIL: get_quote\n", "test_name": "test_Quote", "rerun": "0"}, "9": {"status": "FAIL", "message": "   AssertionError: 401 != 200 : Fail\n", "test_name": "test_balance", "rerun": "0"}, "10": {"status": "FAIL", "message": "       json.decoder.JSONDecodeError: Expecting value: line 1 column 1 (char 0)\n               requests.exceptions.JSONDecodeError: Expecting value: line 1 column 1 (char 0)\n", "test_name": "test_get_beneficiary", "rerun": "0"}}, "suite_name": "API.py"}}}, "date": "April 01, 2024", "start_time": 1711978943.2578871, "total_suite": 1, "status": "FAIL", "status_list": {"pass": "3", "fail": "8", "skip": "0", "error": "0", "xpass": "0", "xfail": "0", "rerun": "0"}, "total_tests": "11"}